LICENSE
MANIFEST.in
README.md
setup.py
parton/__init__.py
parton/__main__.py
parton/cli.py
parton/io.py
parton/pdf.py
parton/test_cli.py
parton/test_lhapdf.py
parton/test_pdf.py
parton/test_plumi.py
parton.egg-info/PKG-INFO
parton.egg-info/SOURCES.txt
parton.egg-info/dependency_links.txt
parton.egg-info/requires.txt
parton.egg-info/top_level.txt