Metadata-Version: 2.1
Name: parton
Version: 0.1
Summary: Python package for parton densities and parton luminosities
Home-page: UNKNOWN
Author: David M. Straub
Author-email: david.straub@tum.de
License: MIT
Platform: UNKNOWN
